pegnet_py/__init__.py
pegnet_py/client.py
pegnet_py/errors.py
pegnet_py/session.py
pegnet_py/fat2/__init__.py
pegnet_py/fat2/consts.py
pegnet_py/fat2/models.py
pegnet_py-0.0.2.dist-info/LICENSE
pegnet_py-0.0.2.dist-info/METADATA
pegnet_py-0.0.2.dist-info/WHEEL
pegnet_py-0.0.2.dist-info/top_level.txt
pegnet_py-0.0.2.dist-info/RECORD
