Metadata-Version: 2.1
Name: pegnet-py
Version: 0.0.2
Summary: Python client library for the pegnetd API
Home-page: https://github.com/pegnet/pegnet-py
License: MIT License
Platform: OS Independent
Classifier: Development Status :: 4 - Beta
Classifier: Intended Audience :: Developers
Classifier: License :: OSI Approved :: MIT License
Classifier: Operating System :: OS Independent
Classifier: Programming Language :: Python :: 3.5
Classifier: Programming Language :: Python :: 3.6
Classifier: Programming Language :: Python :: 3.7
Classifier: Topic :: Internet :: WWW/HTTP
Classifier: Topic :: Security
Classifier: Topic :: Security :: Cryptography
Classifier: Topic :: Software Development
Classifier: Topic :: System :: Monitoring
Requires-Dist: requests (>=2.20.0)
Requires-Dist: factom-api
Requires-Dist: factom-keys
